srd/__init__.py
srd/actors.py
srd/calculators.py
srd/discrete.py
srd/payroll.py
srd/testing.py
srd/tools.py
srd/assistance/__init__.py
srd/assistance/programs.py
srd/assistance/template.py
srd/assistance/params/assistance_2016.csv
srd/assistance/params/assistance_2017.csv
srd/assistance/params/assistance_2018.csv
srd/assistance/params/assistance_2019.csv
srd/assistance/params/assistance_2020.csv
srd/assistance/params/assistance_2021.csv
srd/assistance/params/assistance_2022.csv
srd/covid/__init__.py
srd/covid/programs.py
srd/covid/template.py
srd/covid/params/measures_2020.csv
srd/covid/params/measures_2021.csv
srd/covid/params/measures_2022.csv
srd/ei/__init__.py
srd/ei/programs.py
srd/ei/template.py
srd/ei/params/parameters_2016.csv
srd/ei/params/parameters_2017.csv
srd/ei/params/parameters_2018.csv
srd/ei/params/parameters_2019.csv
srd/ei/params/parameters_2020.csv
srd/ei/params/parameters_2021.csv
srd/ei/params/parameters_2022.csv
srd/federal/__init__.py
srd/federal/forms.py
srd/federal/template.py
srd/federal/params/fed_witb_on_2016.csv
srd/federal/params/fed_witb_on_2017.csv
srd/federal/params/fed_witb_on_2018.csv
srd/federal/params/fed_witb_on_2019.csv
srd/federal/params/fed_witb_on_2020.csv
srd/federal/params/fed_witb_on_2021.csv
srd/federal/params/fed_witb_on_2022.csv
srd/federal/params/fed_witb_qc_2016.csv
srd/federal/params/fed_witb_qc_2017.csv
srd/federal/params/fed_witb_qc_2018.csv
srd/federal/params/fed_witb_qc_2019.csv
srd/federal/params/fed_witb_qc_2020.csv
srd/federal/params/fed_witb_qc_2021.csv
srd/federal/params/fed_witb_qc_2022.csv
srd/federal/params/federal_2016.csv
srd/federal/params/federal_2017.csv
srd/federal/params/federal_2018.csv
srd/federal/params/federal_2019.csv
srd/federal/params/federal_2020.csv
srd/federal/params/federal_2021.csv
srd/federal/params/federal_2022.csv
srd/federal/params/schedule_2016.csv
srd/federal/params/schedule_2017.csv
srd/federal/params/schedule_2018.csv
srd/federal/params/schedule_2019.csv
srd-1.3.0.dist-info/LICENSE
srd-1.3.0.dist-info/METADATA
srd-1.3.0.dist-info/WHEEL
srd-1.3.0.dist-info/top_level.txt
srd-1.3.0.dist-info/RECORD
