Metadata-Version: 2.1
Name: srd
Version: 1.3.0
Summary: Modele de simulation du revenu disponible Quebec
Home-page: https://creei-models.github.io/srd/
Author: Equipe CREEi
Author-email: pierre-carl.michaud@hec.ca
License: UNKNOWN
Platform: UNKNOWN
Classifier: Programming Language :: Python :: 3
Classifier: License :: OSI Approved :: MIT License
Classifier: Operating System :: OS Independent
Requires-Python: >=3.6
License-File: LICENSE
Requires-Dist: pandas
Requires-Dist: numba
Requires-Dist: numpy
Requires-Dist: xlrd
Requires-Dist: srpp
